__init__.py
aigauntlet/BiasedEvaluatorTrial.py
aigauntlet/QuickPrivacyTrial.py
aigauntlet/__init__.py
aigauntlet/_utils.py
aigauntlet/registry.py
aigauntlet/url_utils.py
aigauntlet/utils/__init__.py
aigauntlet/utils/chatbot.py
aigauntlet-0.1.8.dist-info/licenses/LICENSE
utils/chatbot.py
aigauntlet-0.1.8.dist-info/METADATA
aigauntlet-0.1.8.dist-info/WHEEL
aigauntlet-0.1.8.dist-info/top_level.txt
aigauntlet-0.1.8.dist-info/RECORD
