Metadata-Version: 2.4
Name: aigauntlet
Version: 0.1.8
Summary: A library to locally run evaluation tests on AI agents and systems
Author: Actualization AI
License:                     GNU GENERAL PUBLIC LICENSE
Project-URL: Repository, https://github.com/actualization-ai/aigauntlet
Project-URL: Bug Tracker, https://github.com/actualization-ai/aigauntlet/issues
Classifier: Development Status :: 3 - Alpha
Classifier: Intended Audience :: Developers
Classifier: Programming Language :: Python :: 3
Classifier: Programming Language :: Python :: 3.12
Classifier: License :: OSI Approved :: MIT License
Classifier: Operating System :: OS Independent
Requires-Python: >=3.12
License-File: LICENSE
Requires-Dist: anthropic>=0.49.0
Requires-Dist: load-dotenv>=0.1.0
Requires-Dist: nbformat>=5.10.4
Requires-Dist: numpy>=2.2.2
Requires-Dist: openai>=1.60.0
Requires-Dist: plotly>=6.0.0
Requires-Dist: pydantic>=2.10.5
Requires-Dist: python-dotenv>=1.0.1
Requires-Dist: requests>=2.32.3
Requires-Dist: together==1.3.11
Requires-Dist: types-requests>=2.32.0.20241016
Dynamic: license-file
